MANIFEST.in
README.md
setup.py
asset_engine/__init__.py
asset_engine/conf.py
asset_engine/bsetup/__init__.py
asset_engine/bsetup/blender_register.py
asset_engine/bsetup/developer_utils.py
asset_engine/bsetup/handlers.py
asset_engine/bsetup/preferences.py
asset_engine/pipe/__init__.py
asset_engine/pipe/path_lib/__init__.py
asset_engine/pipe/path_lib/asset_formulas.txt
asset_engine/pipe/path_lib/formula_manager.py
asset_engine/pipe/path_lib/pipeline_formulas.txt
asset_engine/pipe/path_lib/project_formulas.txt
asset_engine/pipe/pipe_core/__init__.py
asset_engine/pipe/pipe_core/pipe_context.py
asset_engine/pipe/pipe_core/pipe_enums.py
asset_engine/pipe/pipe_core/pipe_object.py
asset_engine/pipe/pipe_core/pipe_utils.py
asset_engine/pipe/pipe_core/publish_object.py
asset_engine/pipe/pipe_core/type_object.py
asset_engine/pipe/pipe_data/__init__.py
asset_engine/pipe/pipe_data/config.py
asset_engine/pipe/pipe_data/mt_data.py
asset_engine/pipe/pipe_data/mt_object.py
asset_engine/pipe/pipe_utils/__init__.py
asset_engine/utils/__init__.py
asset_engine/utils/butils.py
asset_engine/utils/enum_items.py
asset_engine/utils/io.py
asset_engine/utils/server_threading.py
bpy_asset_engine.egg-info/PKG-INFO
bpy_asset_engine.egg-info/SOURCES.txt
bpy_asset_engine.egg-info/dependency_links.txt
bpy_asset_engine.egg-info/not-zip-safe
bpy_asset_engine.egg-info/top_level.txt