Metadata-Version: 1.2
Name: bpy-asset-engine
Version: 1.0.0
Summary: Blender Asset Engine Library
Home-page: https://gitlab.com/lvxejay/asset_engine
Author: Jared Webber
Author-email: info@onelvxe.com
License: GNU GPLv3
Keywords: blender bpy asset engine pipeline
Platform: UNKNOWN
Requires-Python: ~=3.5
